{
    "key": "group_5496b45b6a1de",
    "title": "Contenuto Sezione",
    "fields": [
        {
            "key": "field_5496b4ae4b8a4",
            "label": "Colonne",
            "name": "flexible_columns",
            "prefix": "",
            "type": "flexible_content",
            "instructions": "",
            "required": 0,
            "conditional_logic": 0,
            "wrapper": {
                "width": "",
                "class": "",
                "id": ""
            },
            "button_label": "Aggiungi Colonna",
            "min": "",
            "max": "",
            "layouts": [
                {
                    "key": "5496b4b1c9d74",
                    "name": "column-11",
                    "label": "Colonna 1\/1",
                    "display": "block",
                    "sub_fields": [
                        {
                            "key": "field_5496b4f24b8a5",
                            "label": "Contenuto",
                            "name": "contenuto",
                            "prefix": "",
                            "type": "post_object",
                            "instructions": "",
                            "required": 0,
                            "conditional_logic": 0,
                            "wrapper": {
                                "width": "",
                                "class": "",
                                "id": ""
                            },
                            "post_type": [
                                "scm-modules"
                            ],
                            "taxonomy": "",
                            "allow_null": 0,
                            "multiple": 0,
                            "return_format": "object",
                            "ui": 1
                        }
                    ],
                    "min": "",
                    "max": ""
                },
                {
                    "key": "5496b5764b8a6",
                    "name": "column-12",
                    "label": "Colonna 1\/2",
                    "display": "block",
                    "sub_fields": [
                        {
                            "key": "field_5496b5764b8a7",
                            "label": "Contenuto",
                            "name": "contenuto",
                            "prefix": "",
                            "type": "post_object",
                            "instructions": "",
                            "required": 0,
                            "conditional_logic": 0,
                            "wrapper": {
                                "width": "",
                                "class": "",
                                "id": ""
                            },
                            "post_type": [
                                "scm-modules"
                            ],
                            "taxonomy": "",
                            "allow_null": 0,
                            "multiple": 0,
                            "return_format": "object",
                            "ui": 1
                        }
                    ],
                    "min": "",
                    "max": ""
                },
                {
                    "key": "5496b5844b8a8",
                    "name": "column-13",
                    "label": "Colonna 1\/3",
                    "display": "block",
                    "sub_fields": [
                        {
                            "key": "field_5496b5844b8a9",
                            "label": "Contenuto",
                            "name": "contenuto",
                            "prefix": "",
                            "type": "post_object",
                            "instructions": "",
                            "required": 0,
                            "conditional_logic": 0,
                            "wrapper": {
                                "width": "",
                                "class": "",
                                "id": ""
                            },
                            "post_type": [
                                "scm-modules"
                            ],
                            "taxonomy": "",
                            "allow_null": 0,
                            "multiple": 0,
                            "return_format": "object",
                            "ui": 1
                        }
                    ],
                    "min": "",
                    "max": ""
                },
                {
                    "key": "5496b5914b8aa",
                    "name": "column-14",
                    "label": "Colonna 1\/4",
                    "display": "block",
                    "sub_fields": [
                        {
                            "key": "field_5496b5914b8ab",
                            "label": "Contenuto",
                            "name": "contenuto",
                            "prefix": "",
                            "type": "post_object",
                            "instructions": "",
                            "required": 0,
                            "conditional_logic": 0,
                            "wrapper": {
                                "width": "",
                                "class": "",
                                "id": ""
                            },
                            "post_type": [
                                "scm-modules"
                            ],
                            "taxonomy": "",
                            "allow_null": 0,
                            "multiple": 0,
                            "return_format": "object",
                            "ui": 1
                        }
                    ],
                    "min": "",
                    "max": ""
                },
                {
                    "key": "5496b81ef8fde",
                    "name": "column-15",
                    "label": "Colonna 1\/5",
                    "display": "block",
                    "sub_fields": [
                        {
                            "key": "field_5496b81ef8fdf",
                            "label": "Contenuto",
                            "name": "contenuto",
                            "prefix": "",
                            "type": "post_object",
                            "instructions": "",
                            "required": 0,
                            "conditional_logic": 0,
                            "wrapper": {
                                "width": "",
                                "class": "",
                                "id": ""
                            },
                            "post_type": [
                                "scm-modules"
                            ],
                            "taxonomy": "",
                            "allow_null": 0,
                            "multiple": 0,
                            "return_format": "object",
                            "ui": 1
                        }
                    ],
                    "min": "",
                    "max": ""
                },
                {
                    "key": "5496b84efd661",
                    "name": "column-16",
                    "label": "Colonna 1\/6",
                    "display": "block",
                    "sub_fields": [
                        {
                            "key": "field_5496b84efd662",
                            "label": "Contenuto",
                            "name": "contenuto",
                            "prefix": "",
                            "type": "post_object",
                            "instructions": "",
                            "required": 0,
                            "conditional_logic": 0,
                            "wrapper": {
                                "width": "",
                                "class": "",
                                "id": ""
                            },
                            "post_type": [
                                "scm-modules"
                            ],
                            "taxonomy": "",
                            "allow_null": 0,
                            "multiple": 0,
                            "return_format": "object",
                            "ui": 1
                        }
                    ],
                    "min": "",
                    "max": ""
                },
                {
                    "key": "5496b868fd663",
                    "name": "column-23",
                    "label": "Colonna 2\/3",
                    "display": "block",
                    "sub_fields": [
                        {
                            "key": "field_5496b868fd664",
                            "label": "Contenuto",
                            "name": "contenuto",
                            "prefix": "",
                            "type": "post_object",
                            "instructions": "",
                            "required": 0,
                            "conditional_logic": 0,
                            "wrapper": {
                                "width": "",
                                "class": "",
                                "id": ""
                            },
                            "post_type": [
                                "scm-modules"
                            ],
                            "taxonomy": "",
                            "allow_null": 0,
                            "multiple": 0,
                            "return_format": "object",
                            "ui": 1
                        }
                    ],
                    "min": "",
                    "max": ""
                },
                {
                    "key": "5496b879fd665",
                    "name": "column-34",
                    "label": "Colonna 3\/4",
                    "display": "block",
                    "sub_fields": [
                        {
                            "key": "field_5496b879fd666",
                            "label": "Contenuto",
                            "name": "contenuto",
                            "prefix": "",
                            "type": "post_object",
                            "instructions": "",
                            "required": 0,
                            "conditional_logic": 0,
                            "wrapper": {
                                "width": "",
                                "class": "",
                                "id": ""
                            },
                            "post_type": [
                                "scm-modules"
                            ],
                            "taxonomy": "",
                            "allow_null": 0,
                            "multiple": 0,
                            "return_format": "object",
                            "ui": 1
                        }
                    ],
                    "min": "",
                    "max": ""
                },
                {
                    "key": "5496b87ffd667",
                    "name": "column-25",
                    "label": "Colonna 2\/5",
                    "display": "block",
                    "sub_fields": [
                        {
                            "key": "field_5496b87ffd668",
                            "label": "Contenuto",
                            "name": "contenuto",
                            "prefix": "",
                            "type": "post_object",
                            "instructions": "",
                            "required": 0,
                            "conditional_logic": 0,
                            "wrapper": {
                                "width": "",
                                "class": "",
                                "id": ""
                            },
                            "post_type": [
                                "scm-modules"
                            ],
                            "taxonomy": "",
                            "allow_null": 0,
                            "multiple": 0,
                            "return_format": "object",
                            "ui": 1
                        }
                    ],
                    "min": "",
                    "max": ""
                },
                {
                    "key": "5496b88cfd669",
                    "name": "column-35",
                    "label": "Colonna 3\/5",
                    "display": "block",
                    "sub_fields": [
                        {
                            "key": "field_5496b88cfd66a",
                            "label": "Contenuto",
                            "name": "contenuto",
                            "prefix": "",
                            "type": "post_object",
                            "instructions": "",
                            "required": 0,
                            "conditional_logic": 0,
                            "wrapper": {
                                "width": "",
                                "class": "",
                                "id": ""
                            },
                            "post_type": [
                                "scm-modules"
                            ],
                            "taxonomy": "",
                            "allow_null": 0,
                            "multiple": 0,
                            "return_format": "object",
                            "ui": 1
                        }
                    ],
                    "min": "",
                    "max": ""
                },
                {
                    "key": "5496b88ffd66b",
                    "name": "column-45",
                    "label": "Colonna 4\/5",
                    "display": "block",
                    "sub_fields": [
                        {
                            "key": "field_5496b88ffd66c",
                            "label": "Contenuto",
                            "name": "contenuto",
                            "prefix": "",
                            "type": "post_object",
                            "instructions": "",
                            "required": 0,
                            "conditional_logic": 0,
                            "wrapper": {
                                "width": "",
                                "class": "",
                                "id": ""
                            },
                            "post_type": [
                                "scm-modules"
                            ],
                            "taxonomy": "",
                            "allow_null": 0,
                            "multiple": 0,
                            "return_format": "object",
                            "ui": 1
                        }
                    ],
                    "min": "",
                    "max": ""
                },
                {
                    "key": "5496b897fd66d",
                    "name": "column-56",
                    "label": "Colonna 5\/6",
                    "display": "block",
                    "sub_fields": [
                        {
                            "key": "field_5496b897fd66e",
                            "label": "Contenuto",
                            "name": "contenuto",
                            "prefix": "",
                            "type": "post_object",
                            "instructions": "",
                            "required": 0,
                            "conditional_logic": 0,
                            "wrapper": {
                                "width": "",
                                "class": "",
                                "id": ""
                            },
                            "post_type": [
                                "scm-modules"
                            ],
                            "taxonomy": "",
                            "allow_null": 0,
                            "multiple": 0,
                            "return_format": "object",
                            "ui": 1
                        }
                    ],
                    "min": "",
                    "max": ""
                }
            ]
        }
    ],
    "location": [
        [
            {
                "param": "post_type",
                "operator": "==",
                "value": "scm-sections"
            }
        ]
    ],
    "menu_order": 211,
    "position": "normal",
    "style": "default",
    "label_placement": "top",
    "instruction_placement": "label",
    "hide_on_screen": [
        "excerpt",
        "custom_fields",
        "discussion",
        "comments",
        "revisions",
        "slug",
        "author",
        "format",
        "page_attributes",
        "featured_image",
        "categories",
        "tags",
        "send-trackbacks"
    ],
    "modified": 1421070918
}