{
    "key": "group_549608d92368b",
    "title": "Rassegna Stampa",
    "fields": [
        {
            "key": "field_5474d1c484720",
            "label": "Tipo",
            "name": "",
            "prefix": "",
            "type": "tab",
            "instructions": "",
            "required": 0,
            "conditional_logic": 0,
            "wrapper": {
                "width": "",
                "class": "",
                "id": ""
            },
            "placement": "top"
        },
        {
            "key": "field_538b7e03e44b8",
            "label": "Seleziona il tipo di Rassegna Stampa",
            "name": "rassegne-stampa_tipo",
            "prefix": "",
            "type": "radio",
            "instructions": "",
            "required": 1,
            "conditional_logic": 0,
            "wrapper": {
                "width": "",
                "class": "",
                "id": ""
            },
            "choices": {
                "File": "File",
                "Link": "Link"
            },
            "other_choice": 0,
            "save_other_choice": 0,
            "default_value": "File",
            "layout": "vertical"
        },
        {
            "key": "field_5474d32084724",
            "label": "Articolo",
            "name": "",
            "prefix": "",
            "type": "tab",
            "instructions": "",
            "required": 0,
            "conditional_logic": 0,
            "wrapper": {
                "width": "",
                "class": "",
                "id": ""
            },
            "placement": "top"
        },
        {
            "key": "field_538b7e57e44b9",
            "label": "Carica un File",
            "name": "rassegne-stampa_file",
            "prefix": "",
            "type": "file",
            "instructions": "",
            "required": 0,
            "conditional_logic": [
                [
                    {
                        "field": "field_538b7e03e44b8",
                        "operator": "==",
                        "value": "File"
                    }
                ]
            ],
            "wrapper": {
                "width": "",
                "class": "",
                "id": ""
            },
            "library": "all",
            "return_format": "url",
            "min_size": 0,
            "max_size": 0,
            "mime_types": ""
        },
        {
            "key": "field_538b7e75e44ba",
            "label": "Inserisci un Link",
            "name": "rassegne-stampa_link",
            "prefix": "",
            "type": "text",
            "instructions": "",
            "required": 0,
            "conditional_logic": [
                [
                    {
                        "field": "field_538b7e03e44b8",
                        "operator": "==",
                        "value": "Link"
                    }
                ]
            ],
            "wrapper": {
                "width": "",
                "class": "",
                "id": ""
            },
            "default_value": "",
            "placeholder": "www.esempio.it",
            "prepend": "http:\/\/",
            "append": "",
            "formatting": "none",
            "maxlength": "",
            "readonly": 0,
            "disabled": 0
        },
        {
            "key": "field_5474d28184721",
            "label": "Autore",
            "name": "",
            "prefix": "",
            "type": "tab",
            "instructions": "",
            "required": 0,
            "conditional_logic": 0,
            "wrapper": {
                "width": "",
                "class": "",
                "id": ""
            },
            "placement": "top"
        },
        {
            "key": "field_538b7da2e44b5",
            "label": "Inserisci un autore",
            "name": "rassegne-stampa_autore",
            "prefix": "",
            "type": "text",
            "instructions": "",
            "required": 0,
            "conditional_logic": 0,
            "wrapper": {
                "width": "",
                "class": "",
                "id": ""
            },
            "default_value": "",
            "placeholder": "",
            "prepend": "di",
            "append": "",
            "formatting": "none",
            "maxlength": "",
            "readonly": 0,
            "disabled": 0
        },
        {
            "key": "field_5474d29584722",
            "label": "Testata",
            "name": "",
            "prefix": "",
            "type": "tab",
            "instructions": "",
            "required": 0,
            "conditional_logic": 0,
            "wrapper": {
                "width": "",
                "class": "",
                "id": ""
            },
            "placement": "top"
        },
        {
            "key": "field_538b7dd1e44b6",
            "label": "Nome della Testata",
            "name": "rassegne-stampa_testata",
            "prefix": "",
            "type": "text",
            "instructions": "",
            "required": 0,
            "conditional_logic": 0,
            "wrapper": {
                "width": "",
                "class": "",
                "id": ""
            },
            "default_value": "",
            "placeholder": "",
            "prepend": "Pubblicato su",
            "append": "",
            "formatting": "none",
            "maxlength": "",
            "readonly": 0,
            "disabled": 0
        },
        {
            "key": "field_5474d30c84723",
            "label": "Data",
            "name": "",
            "prefix": "",
            "type": "tab",
            "instructions": "",
            "required": 0,
            "conditional_logic": 0,
            "wrapper": {
                "width": "",
                "class": "",
                "id": ""
            },
            "placement": "top"
        },
        {
            "key": "field_538b7df3e44b7",
            "label": "Seleziona una Data",
            "name": "rassegne-stampa_data",
            "prefix": "",
            "type": "date_picker",
            "instructions": "",
            "required": 0,
            "conditional_logic": 0,
            "wrapper": {
                "width": "",
                "class": "",
                "id": ""
            },
            "first_day": 1,
            "return_format": "Ymd",
            "display_format": "d\/m\/Y"
        }
    ],
    "location": [
        [
            {
                "param": "post_type",
                "operator": "==",
                "value": "post"
            },
            {
                "param": "post_type",
                "operator": "!=",
                "value": "post"
            }
        ]
    ],
    "menu_order": 500,
    "position": "normal",
    "style": "default",
    "label_placement": "top",
    "instruction_placement": "label",
    "hide_on_screen": [
        "the_content",
        "excerpt",
        "custom_fields",
        "discussion",
        "comments",
        "revisions",
        "slug",
        "author",
        "format",
        "page_attributes",
        "featured_image",
        "categories",
        "tags",
        "send-trackbacks"
    ],
    "modified": 1425027418,
    "local": "json"
}